{
    "init_display":{
        "1":"y",
        "2":"y",
        "3":"y",
        "4":"r",
        "5":"g",
        "6":"r",
        "7":"g",
        "8":"r",
        "9":"y",
        "10":"g",
        "11":"g",
        "12":"r",
        "13":"r",
        "14":"y",
        "15":"y",
        "16":"y",
        "pos":13
    },


    "algorithm":
    {
        "state":{
            "1":{
                "red":{
                    "next_color":"g",
                    "movement":"l",
                    "state":2
                },
                "green":{
                    "next_color":"r",
                    "movement":"l",
                    "state":1
                },
                "yellow":{
                    "next_color":"y",
                    "movement":"0",
                    "state":1
                }
            },
            "2":{
                "red":{
                    "next_color":"r",
                    "movement":"l",
                    "state":2
                },
                "green":{
                    "next_color":"g",
                    "movement":"l",
                    "state":2
                },
                "yellow":{
                    "next_color":"y",
                    "movement":"l",
                    "state":3
                }
            },
            "3":{
                "red":{
                    "next_color":"g",
                    "movement":"l",
                    "state":3
                },
                "green":{
                    "next_color":"r",
                    "movement":"r",
                    "state":4
                },
                "yellow":{
                    "next_color":"r",
                    "movement":"r",
                    "state":4
                }
            },
            "4":{
                "red":{
                    "next_color":"r",
                    "movement":"r",
                    "state":4
                },
                "green":{
                    "next_color":"g",
                    "movement":"r",
                    "state":4
                },
                "yellow":{
                    "next_color":"y",
                    "movement":"r",
                    "state":5
                }
            },
            "5":{
                "red":{
                    "next_color":"r",
                    "movement":"r",
                    "state":6
                },
                "green":{
                    "next_color":"g",
                    "movement":"r",
                    "state":5
                },
                "yellow":{
                    "next_color":"y",
                    "movement":"0",
                    "state":5
                }
            },
            "6":{
                "red":{
                    "next_color":"r",
                    "movement":"r",
                    "state":6
                },
                "green":{
                    "next_color":"g",
                    "movement":"r",
                    "state":6
                },
                "yellow":{
                    "next_color":"y",
                    "movement":"r",
                    "state":1
                }
            }
        }
    }
}